<?xml version="1.0" encoding="UTF-8"?>
<tour appversion="6.1.15" apprev="18116" start="node6">
  <panorama id="node6">
    <input levelingpitch="0" levelingroll="0" leveltileurl="tiles/node6/cf_%c/l_%l/c_%x/tile_%y.jpg" width="2235" height="2235" leveltilesize="510" levelbias="0.400" levelbiashidpi="1.000" overlap="1">
      <level width="2235" height="2235" preload="0" predecode="0"/>
      <level width="1117" height="1117" preload="0" predecode="0"/>
      <level width="558" height="558" preload="0" predecode="0"/>
      <level width="279" height="279" preload="1" predecode="1"/>
      <preview color="0x808080" strip="1"/>
    </input>
    <view pannorth="0" fovmode="0">
      <start tilt="0" projection="4" fov="70" pan="0"/>
      <flyin tilt="-90" projection="9" fov="170" pan="0"/>
      <min tilt="-90" pan="0" fovpixel="2"/>
      <max tilt="90" fovstereographic="270" scaletofit="1" fov="120" pan="360" fovfisheye="360"/>
    </view>
    <userdata source="" comment="" tags="01 Panos Realistic" title="Menu" latitude="" longitude="" heading="0" nodeid="node6" customnodeid="" info="" description="" copyright="" author="" datetime="6/7/22 3:47 AM"/>
    <hotspots width="180" height="20" wordwrap="1">
      <label background="1" bordercolor="0x000000" backgroundalpha="1" width="180" height="20" backgroundcolor="0xffffff" textalpha="1" wordwrap="1" textcolor="0x000000" borderalpha="1" enabled="1" border="1" borderradius="1"/>
      <polystyle bordercolor="0x0000ff" backgroundalpha="0.25098" mode="0" backgroundcolor="0x0000ff" handcursor="1" borderalpha="1"/>
      <hotspot tilt="-17.21" customimagewidth="279" title="Intro_Video" skinid="Menu Tour" customimageheight="131" use3D="0" url="{node4}" distance3D="1594.49" fov="10" pan="-21.79" description="" customimage="media/Tour Mode-01.png" id="Point03" target=""/>
      <hotspot tilt="-17.11" customimagewidth="279" title="" skinid="Menu Story" customimageheight="131" use3D="0" url="{node1}" distance3D="1594.49" fov="10" pan="21.9" description="" customimage="media/Story Mode-01.png" id="Point01" target=""/>
    </hotspots>
    <media>
      <sound tilt="24.020" level="0.700" nodechangekeep="0" ambientlevel="0.000" tiltsize="10.000" mode="2" loop="5" field="90.000" pan="-321.650" startmutedmobile="0" id="Element01" pansize="10.000">
        <source url="media/piano-moment-9835.mp3"/>
      </sound>
      <video stretch="1.000" mode="3" tiltsize="10.000" startmutedmobile="0" width="980" clickmode="0" rotx="-3.000" loop="5" nodechangekeep="0" ambientlevel="0.000" fov="26.630" pan="-337.340" rotz="0.000" field="90.000" id="Element02" height="1270" roty="2.000" pansize="10.000" tilt="6.490" handcursor="0" level="1.000">
        <source url="media/Video_1.mp4"/>
      </video>
      <video stretch="1.000" mode="3" tiltsize="10.000" startmutedmobile="0" width="980" clickmode="0" rotx="0.000" loop="5" nodechangekeep="0" ambientlevel="0.000" fov="25.610" pan="-22.090" rotz="0.000" field="90.000" id="Element03" height="1270" roty="0.000" pansize="10.000" tilt="5.080" handcursor="0" level="1.000">
        <source url="media/Video_2.mp4"/>
      </video>
    </media>
    <transition zoomspeed="2" zoomfov="20" zoomafterinfov="90" zoomin="0" zoomout="0" zoomafteroutfov="20" softedge="0" zoomoutpause="1" blendcolor="0x000000" type="crossdissolve" blendtime="1" enabled="1"/>
    <animation useinautorotation="0" animsequence="Animation01" syncanimationwithvideo="0"/>
    <control contextvr="1" lockedkeyboard="0" contextfullscreen="1" lockedmouse="0" lockedkeyboardzoom="0" sensitivity="8" invertwheel="0" speedwheel="1" rubberband="0" dblclickfullscreen="0" simulatemass="1" lockedwheel="0" invertcontrol="1" contextprojections="0"/>
  </panorama>
  <panorama id="node4">
    <input levelingpitch="0" levelingroll="0" leveltileurl="tiles/node4/cf_%c/l_%l/c_%x/tile_%y.jpg" width="2235" height="2235" leveltilesize="510" levelbias="0.400" levelbiashidpi="1.000" overlap="1">
      <level width="2235" height="2235" preload="0" predecode="0"/>
      <level width="1117" height="1117" preload="0" predecode="0"/>
      <level width="558" height="558" preload="0" predecode="0"/>
      <level width="279" height="279" preload="1" predecode="1"/>
      <preview color="0x808080" strip="1"/>
    </input>
    <view pannorth="0" fovmode="0">
      <start tilt="-12.5922" projection="4" fov="94.6134" pan="106.786"/>
      <flyin tilt="-90" projection="9" fov="170" pan="0"/>
      <min tilt="-90" pan="0" fovpixel="2"/>
      <max tilt="90" fovstereographic="270" scaletofit="1" fov="120" pan="360" fovfisheye="360"/>
    </view>
    <userdata source="" comment="" tags="01 Panos Realistic" title="Intro_Video" latitude="" longitude="" heading="0" nodeid="node4" customnodeid="" info="" description="" copyright="" author="" datetime="6/7/22 3:47 AM"/>
    <hotspots width="180" height="20" wordwrap="1">
      <label background="1" bordercolor="0x000000" backgroundalpha="1" width="180" height="20" backgroundcolor="0xffffff" textalpha="1" wordwrap="1" textcolor="0x000000" borderalpha="1" enabled="1" border="1" borderradius="1"/>
      <polystyle bordercolor="0x0000ff" backgroundalpha="0.25098" mode="0" backgroundcolor="0x0000ff" handcursor="1" borderalpha="1"/>
      <hotspot tilt="-20.8" customimagewidth="279" title="" skinid="ht_node" customimageheight="131" use3D="0" url="{node1}" distance3D="1594.49" fov="10" pan="-280.34" description="" customimage="media/next-01.png" id="Point01" target=""/>
    </hotspots>
    <media>
      <video stretch="1.000" mode="3" tiltsize="10.000" startmutedmobile="0" width="3792" clickmode="0" rotx="1.000" loop="1" nodechangekeep="0" ambientlevel="0.000" fov="28.300" pan="-254.020" rotz="0.000" field="90.000" id="Element01" height="4694" roty="1.000" pansize="10.000" tilt="1.090" handcursor="0" level="1.000">
        <source url="media/intro_3-3_480.mov"/>
      </video>
      <video stretch="1.000" mode="3" tiltsize="10.000" startmutedmobile="0" width="3792" clickmode="0" rotx="-8.000" loop="1" nodechangekeep="0" ambientlevel="0.000" fov="24.938" pan="-225.890" rotz="0.000" field="90.000" id="Element01" height="4694" roty="1.000" pansize="10.000" tilt="1.230" handcursor="0" level="1.000">
        <source url="media/intro_1-3_480.mov"/>
      </video>
      <video stretch="1.000" mode="3" tiltsize="10.000" startmutedmobile="0" width="3792" clickmode="0" rotx="-10.000" loop="1" nodechangekeep="0" ambientlevel="0.000" fov="22.270" pan="-279.930" rotz="0.000" field="90.000" id="Element01" height="4694" roty="1.000" pansize="10.000" tilt="0.870" handcursor="0" level="1.000">
        <source url="media/intro_2-3_480.mov"/>
      </video>
      <sound tilt="25.910" level="1.000" nodechangekeep="0" ambientlevel="0.000" tiltsize="10.000" mode="2" loop="1" field="90.000" pan="-267.000" startmutedmobile="0" id="Element02" pansize="10.000">
        <source url="media/dwightdeisenhowerddayaddress.mp3"/>
      </sound>
    </media>
    <transition zoomspeed="2" zoomfov="20" zoomafterinfov="90" zoomin="0" zoomout="0" zoomafteroutfov="20" softedge="0" zoomoutpause="1" blendcolor="0x000000" type="crossdissolve" blendtime="1" enabled="1"/>
    <animation useinautorotation="0" animsequence="Animation01" syncanimationwithvideo="0"/>
    <control contextvr="1" lockedkeyboard="0" contextfullscreen="1" lockedmouse="0" lockedkeyboardzoom="0" sensitivity="8" invertwheel="0" speedwheel="1" rubberband="0" dblclickfullscreen="0" simulatemass="1" lockedwheel="0" invertcontrol="1" contextprojections="0"/>
  </panorama>
  <panorama id="node1">
    <input levelingpitch="0" levelingroll="0" leveltileurl="tiles/node1/cf_%c/l_%l/c_%x/tile_%y.jpg" width="2204" height="2204" leveltilesize="510" levelbias="0.400" levelbiashidpi="1.000" overlap="1">
      <level width="2204" height="2204" preload="0" predecode="0"/>
      <level width="1102" height="1102" preload="0" predecode="0"/>
      <level width="551" height="551" preload="0" predecode="0"/>
      <level width="275" height="275" preload="1" predecode="1"/>
      <preview color="0x808080" strip="1"/>
    </input>
    <view pannorth="0" fovmode="0">
      <start tilt="-1.88927" projection="4" fov="94.6134" pan="102.769"/>
      <flyin tilt="-90" projection="9" fov="170" pan="0"/>
      <min tilt="-90" pan="0" fovpixel="2"/>
      <max tilt="90" fovstereographic="270" scaletofit="1" fov="120" pan="360" fovfisheye="360"/>
    </view>
    <userdata source="" comment="" tags="00 Panos Realistic" title="Beach_1" latitude="" longitude="" heading="0" nodeid="node1" customnodeid="" info="" description="" copyright="" author="" datetime="6/7/22 5:07 AM"/>
    <hotspots width="180" height="20" wordwrap="1">
      <label background="1" bordercolor="0x000000" backgroundalpha="1" width="180" height="20" backgroundcolor="0xffffff" textalpha="1" wordwrap="1" textcolor="0x000000" borderalpha="1" enabled="1" border="1" borderradius="1"/>
      <polystyle bordercolor="0x0000ff" backgroundalpha="0.25098" mode="0" backgroundcolor="0x0000ff" handcursor="1" borderalpha="1"/>
      <hotspot tilt="4.47" title="" skinid="Hotspot 1" url="{node3}" pan="-256.94" description="" id="Point01" target=""/>
    </hotspots>
    <media>
      <sound tilt="14.500" level="1.000" nodechangekeep="0" ambientlevel="1.000" tiltsize="10.000" mode="3" loop="10" field="90.000" pan="-255.500" startmutedmobile="0" id="Element01" pansize="10.000">
        <source url="media/gentle-ocean-waves-birdsong-and-gull-7109.mp3"/>
      </sound>
    </media>
    <transition zoomspeed="2" zoomfov="20" zoomafterinfov="90" zoomin="0" zoomout="0" zoomafteroutfov="20" softedge="0" zoomoutpause="1" blendcolor="0x000000" type="crossdissolve" blendtime="1" enabled="1"/>
    <animation useinautorotation="0" animsequence="Animation01" syncanimationwithvideo="0"/>
    <control contextvr="1" lockedkeyboard="0" contextfullscreen="1" lockedmouse="0" lockedkeyboardzoom="0" sensitivity="8" invertwheel="0" speedwheel="1" rubberband="0" dblclickfullscreen="0" simulatemass="1" lockedwheel="0" invertcontrol="1" contextprojections="0"/>
  </panorama>
  <panorama id="node2">
    <input levelingpitch="0" levelingroll="0" leveltileurl="tiles/node2/cf_%c/l_%l/c_%x/tile_%y.jpg" width="2221" height="2221" leveltilesize="510" levelbias="0.400" levelbiashidpi="1.000" overlap="1">
      <level width="2221" height="2221" preload="0" predecode="0"/>
      <level width="1110" height="1110" preload="0" predecode="0"/>
      <level width="555" height="555" preload="0" predecode="0"/>
      <level width="277" height="277" preload="1" predecode="1"/>
      <preview color="0x808080" strip="1"/>
    </input>
    <view pannorth="0" fovmode="0">
      <start tilt="1.5758" projection="4" fov="70" pan="12.8429"/>
      <flyin tilt="-90" projection="9" fov="170" pan="0"/>
      <min tilt="-90" pan="0" fovpixel="2"/>
      <max tilt="90" fovstereographic="270" scaletofit="1" fov="120" pan="360" fovfisheye="360"/>
    </view>
    <userdata source="" comment="" tags="00 Panos Realistic" title="Beach_3" latitude="" longitude="" heading="0" nodeid="node2" customnodeid="" info="" description="" copyright="" author="" datetime="6/7/22 5:15 AM"/>
    <hotspots width="180" height="20" wordwrap="1">
      <label background="1" bordercolor="0x000000" backgroundalpha="1" width="180" height="20" backgroundcolor="0xffffff" textalpha="1" wordwrap="1" textcolor="0x000000" borderalpha="1" enabled="1" border="1" borderradius="1"/>
      <polystyle bordercolor="0x0000ff" backgroundalpha="0.25098" mode="0" backgroundcolor="0x0000ff" handcursor="1" borderalpha="1"/>
      <hotspot tilt="-21.57" title="" skinid="Hotspot 1" url="{node3}" pan="-298.95" description="" id="Point01" target=""/>
    </hotspots>
    <media>
      <sound tilt="-0.780" level="1.000" nodechangekeep="0" ambientlevel="1.000" tiltsize="10.000" mode="3" loop="3" field="90.000" pan="-319.770" startmutedmobile="0" id="Element01" pansize="10.000">
        <source url="media/gentle-ocean-waves-birdsong-and-gull-7109.mp3"/>
      </sound>
      <sound tilt="46.400" level="0.500" nodechangekeep="0" ambientlevel="0.000" tiltsize="10.000" mode="3" loop="1" field="90.000" pan="-21.220" startmutedmobile="0" id="Element02" pansize="10.000">
        <source url="media/low-airplane-fly-by-90354.mp3"/>
      </sound>
      <sound tilt="1.280" level="0.600" nodechangekeep="0" ambientlevel="0.000" tiltsize="10.000" mode="3" loop="10" field="90.000" pan="-339.470" startmutedmobile="0" id="Element03" pansize="10.000">
        <source url="media/Weapon Ambience World War 2 Battlefield - QuickSounds.com.mp3"/>
      </sound>
      <image tilt="68.990" roty="0.000" rotx="0.000" clickmode="0" rotz="0.000" width="605" height="600" handcursor="0" fov="30.000" pan="-53.630" stretch="1.000" id="Element04">
        <source url="media/605px-C-47_Dakotas_and_paratroops.jpg"/>
      </image>
      <image tilt="0.530" roty="-5.000" rotx="-15.000" clickmode="4" rotz="-1.000" width="1024" height="771" handcursor="0" fov="7.323" pan="-358.080" stretch="1.000" id="Element05">
        <source url="media/omaha_beach_debarquement.jpg"/>
      </image>
    </media>
    <transition zoomspeed="2" zoomfov="20" zoomafterinfov="90" zoomin="0" zoomout="0" zoomafteroutfov="20" softedge="0" zoomoutpause="1" blendcolor="0x000000" type="crossdissolve" blendtime="1" enabled="1"/>
    <animation useinautorotation="0" animsequence="Animation01" syncanimationwithvideo="0"/>
    <control contextvr="1" lockedkeyboard="0" contextfullscreen="1" lockedmouse="0" lockedkeyboardzoom="0" sensitivity="8" invertwheel="0" speedwheel="1" rubberband="0" dblclickfullscreen="0" simulatemass="1" lockedwheel="0" invertcontrol="1" contextprojections="0"/>
  </panorama>
  <panorama id="node3">
    <input levelingpitch="0" levelingroll="0" leveltileurl="tiles/node3/cf_%c/l_%l/c_%x/tile_%y.jpg" width="2220" height="2220" leveltilesize="510" levelbias="0.400" levelbiashidpi="1.000" overlap="1">
      <level width="2220" height="2220" preload="0" predecode="0"/>
      <level width="1110" height="1110" preload="0" predecode="0"/>
      <level width="555" height="555" preload="0" predecode="0"/>
      <level width="277" height="277" preload="1" predecode="1"/>
      <preview color="0x808080" strip="1"/>
    </input>
    <view pannorth="0" fovmode="0">
      <start tilt="0" projection="4" fov="70" pan="0"/>
      <flyin tilt="-90" projection="9" fov="170" pan="0"/>
      <min tilt="-90" pan="0" fovpixel="2"/>
      <max tilt="90" fovstereographic="270" scaletofit="1" fov="120" pan="360" fovfisheye="360"/>
    </view>
    <userdata source="" comment="" tags="00 Panos Realistic" title="Beach_2" latitude="" longitude="" heading="0" nodeid="node3" customnodeid="" info="" description="" copyright="" author="" datetime="6/7/22 5:17 AM"/>
    <hotspots width="180" height="20" wordwrap="1">
      <label background="1" bordercolor="0x000000" backgroundalpha="1" width="180" height="20" backgroundcolor="0xffffff" textalpha="1" wordwrap="1" textcolor="0x000000" borderalpha="1" enabled="1" border="1" borderradius="1"/>
      <polystyle bordercolor="0x0000ff" backgroundalpha="0.25098" mode="0" backgroundcolor="0x0000ff" handcursor="1" borderalpha="1"/>
      <hotspot tilt="2.37" title="" skinid="Hotspot 1" url="{node1}" pan="-288.95" description="" id="Point01" target=""/>
      <hotspot tilt="15.4" title="" skinid="Hotspot 1" url="{node2}" pan="-175.26" description="" id="Point02" target=""/>
    </hotspots>
    <media>
      <sound tilt="4.750" level="1.000" nodechangekeep="0" ambientlevel="1.000" tiltsize="10.000" mode="3" loop="10" field="90.000" pan="-25.060" startmutedmobile="0" id="Element01" pansize="10.000">
        <source url="media/gentle-ocean-waves-birdsong-and-gull-7109.mp3"/>
      </sound>
      <sound tilt="49.620" level="1.000" nodechangekeep="0" ambientlevel="1.000" tiltsize="10.000" mode="3" loop="1" field="90.000" pan="-284.370" startmutedmobile="0" id="Element02" pansize="10.000">
        <source url="media/low-airplane-fly-by-90354.mp3"/>
      </sound>
      <image tilt="-7.250" roty="0.000" rotx="-11.000" clickmode="0" rotz="4.000" width="1800" height="1013" handcursor="0" fov="21.630" pan="-323.400" stretch="1.000" id="Element03">
        <source url="media/barrier.png"/>
      </image>
      <image tilt="74.700" roty="0.000" rotx="0.000" clickmode="0" rotz="0.000" width="605" height="600" handcursor="0" fov="31.570" pan="-82.510" stretch="1.000" id="Element04">
        <source url="media/605px-C-47_Dakotas_and_paratroops.jpg"/>
      </image>
      <image tilt="2.150" roty="3.000" rotx="0.000" clickmode="4" rotz="0.000" width="1200" height="1200" handcursor="0" fov="5.062" pan="-360.640" stretch="1.000" id="Element06">
        <source url="media/hith-tiger-nara-2.jpg"/>
      </image>
      <image tilt="-0.920" roty="25.000" rotx="-5.000" clickmode="4" rotz="4.000" width="841" height="543" handcursor="0" fov="6.850" pan="-324.420" stretch="1.000" id="Element05">
        <source url="media/Pop_up.jpg"/>
      </image>
    </media>
    <transition zoomspeed="2" zoomfov="20" zoomafterinfov="90" zoomin="0" zoomout="0" zoomafteroutfov="20" softedge="0" zoomoutpause="1" blendcolor="0x000000" type="crossdissolve" blendtime="1" enabled="1"/>
    <animation useinautorotation="0" animsequence="Animation01" syncanimationwithvideo="0"/>
    <control contextvr="1" lockedkeyboard="0" contextfullscreen="1" lockedmouse="0" lockedkeyboardzoom="0" sensitivity="8" invertwheel="0" speedwheel="1" rubberband="0" dblclickfullscreen="0" simulatemass="1" lockedwheel="0" invertcontrol="1" contextprojections="0"/>
  </panorama>
  <masternode>
    <userdata source="" comment="" tags="" title="" latitude="" longitude="" heading="0" nodeid="master" customnodeid="" info="" description="" copyright="" author="" datetime=""/>
  </masternode>
</tour>
